tf2_hitsound_manager/__init__.py
tf2_hitsound_manager/main.py
tf2_hitsound_manager/assets/fonts/tf2build.ttf
tf2_hitsound_manager/assets/styles/style.qss
tf2_hitsound_manager/data/custom_sounds.txt
tf2_hitsound_manager/data/related_sounds.csv
tf2_hitsound_manager-1.2.0a1.dist-info/LICENSE
tf2_hitsound_manager-1.2.0a1.dist-info/METADATA
tf2_hitsound_manager-1.2.0a1.dist-info/WHEEL
tf2_hitsound_manager-1.2.0a1.dist-info/entry_points.txt
tf2_hitsound_manager-1.2.0a1.dist-info/top_level.txt
tf2_hitsound_manager-1.2.0a1.dist-info/RECORD
