Metadata-Version: 2.2
Name: tf2-hitsound-manager
Version: 1.2.0a1
Summary: A custom sound manager for Team Fortress 2
Home-page: https://github.com/gitchasing/tf2-hitsound-manager/
Author: gitchasing
License:                     GNU GENERAL PUBLIC LICENSE
License-File: LICENSE
Requires-Dist: pydub~=0.25.1
Requires-Dist: PyQt5~=5.15.11
Requires-Dist: send2trash~=1.8.3
Dynamic: author
Dynamic: description
Dynamic: home-page
Dynamic: license
Dynamic: requires-dist
Dynamic: summary
